{
  "word": "ver",
  "definitions": [
    {
      "category": "verbo transitivo",
      "definitions": [
        "Exercer o sentido da vista sobre.",
        "Olhar para.",
        "Presenciar, assistir a.",
        "Avistar; enxergar.",
        "Encontrar, achar, reconhecer.",
        "Observar, notar, advertir.",
        "Reparar, tomar cuidado em.",
        "Imaginar, fantasiar.",
        "Calcular, supor; ponderar, inferir, deduzir.",
        "Prever.",
        "Visitar.",
        "Escolher.",
        "Percorrer.",
        "Provar.",
        "Conhecer."
      ]
    },
    {
      "category": "verbo pronominal",
      "definitions": [
        "Olhar-se.",
        "Encontrar-se."
      ]
    },
    {
      "category": "nome masculino",
      "definitions": [
        "Parecer; juízo; opinião (ex.: no ver dele, isto é inadmissível ).",
        "O acto de ver."
      ]
    }
  ],
  "error": null
}